grid2fp/__init__.py
grid2fp/grid2fp.py
grid2fp/grid_segment.py
test/__init__.py
test/test_integration.py
grid2fp-0.0.10.dist-info/LICENSE
grid2fp-0.0.10.dist-info/METADATA
grid2fp-0.0.10.dist-info/WHEEL
grid2fp-0.0.10.dist-info/top_level.txt
grid2fp-0.0.10.dist-info/RECORD
