Metadata-Version: 2.1
Name: grid2fp
Version: 0.0.10
Summary: A tool to eat grid diagrams and generate its front projection.
Home-page: https://github.com/Joecstarr/grid2fp
Author: Joe Starr
Keywords: topology,Legendrian,Grid Diagram,knot
Classifier: Programming Language :: Python :: 3
Classifier: License :: OSI Approved :: GNU General Public License (GPL)
Classifier: Operating System :: OS Independent
Classifier: Framework :: IPython
Requires-Python: >=3
License-File: LICENSE
Requires-Dist: drawsvg
